Metadata-Version: 2.1
Name: mac-app-env
Version: 2020.7.1
Summary: set macOS app environment variables (Info.plist LSEnvironment)
Home-page: https://github.com/andrewp-as-is/mac-app-env.py
License: Unlicense
Keywords: mac app env
Platform: UNKNOWN
Classifier: License :: Public Domain
Classifier: Operating System :: MacOS
Classifier: Programming Language :: Python :: 3
